<?xml version="1.0" encoding="UTF-8"?>
<PropertyList>
	<model>
		<name>Navigator Panel</name>
		<path>Aircraft/Tornado/Models/Cockpit/Parts/navigator_ids.xml</path>
	</model>
	<model>
		<name>Cockpit-Common</name>
		<path>Aircraft/Tornado/Models/Cockpit/Cockpit-Common.xml</path>
	</model>
	<model>
		<name>FrontH</name>
		<path>Aircraft/Tornado/Models/Cockpit/FrontUp-IDS.xml</path>
		<offsets>
			<x-m>-4.860</x-m>
			<y-m> 0.000</y-m>
			<z-m>-0.400</z-m>
			<pitch-deg>-10.0</pitch-deg>
		</offsets>
	</model>
	<model>
		<name>Joystick</name>
		<path>Aircraft/Tornado/Models/Cockpit/Parts/joystick_ids.ac</path>
		<offsets>
			<x-m>-4.550</x-m>
			<y-m>0.000</y-m>
			<z-m>-1.100</z-m>
		</offsets>
	</model>
	<animation>
		<type>rotate</type>
		<object-name>Joystick</object-name>
		<property>controls/flight/elevator</property>
		<interpolation>
			<entry>
				<ind>-1.0</ind>
				<dep>14.0</dep>
			</entry>
			<entry>
				<ind>0.0</ind>
				<dep>0.0</dep>
			</entry>
			<entry>
				<ind>1.0</ind>
				<dep>-7.0</dep>
			</entry>
		</interpolation>
		<center>
			<x-m>-4.550</x-m>
			<y-m>0.000</y-m>
			<z-m>-1.100</z-m>
		</center>
		<axis>
			<x>0</x>
			<y>1</y>
			<z>0</z>
		</axis>
	</animation>
	<animation>
		<type>rotate</type>
		<object-name>Joystick</object-name>
		<property>controls/flight/aileron</property>
		<interpolation>
			<entry>
				<ind>-1.0</ind>
				<dep>-10.5</dep>
			</entry>
			<entry>
				<ind>0.0</ind>
				<dep>0.0</dep>
			</entry>
			<entry>
				<ind>1.0</ind>
				<dep>10.5</dep>
			</entry>
		</interpolation>
		<center>
			<x-m>-4.550</x-m>
			<y-m>0.000</y-m>
			<z-m>-1.100</z-m>
		</center>
		<axis>
			<x>-1</x>
			<y>0</y>
			<z>0</z>
		</axis>
	</animation>
	<model>
		<name>RPMD</name>
		<path>Aircraft/Tornado/Models/Cockpit/Instruments/rpmd/rpmd.xml</path>
		<offsets>
			<x-m>-4.835</x-m>
			<y-m>0.000</y-m>
			<z-m>-0.570</z-m>
			<pitch-deg>-10.0</pitch-deg>
		</offsets>
	</model>
</PropertyList>
